<?xml version="1.0" encoding="UTF-8"?>
<databaseChangeLog
        xmlns="http://www.liquibase.org/xml/ns/dbchangelog"
        xmlns:xsi="http://www.w3.org/2001/XMLSchema-instance"
        xsi:schemaLocation="http://www.liquibase.org/xml/ns/dbchangelog http://www.liquibase.org/xml/ns/dbchangelog/dbchangelog-3.1.xsd">

    <!-- JHipster core -->
    <changeSet id="1" author="jhipster">
        <createTable tableName="T_USER">
            <column name="login" type="varchar(50)">
                <constraints primaryKey="true" nullable="false"/>
            </column>
            <column name="password" type="varchar(100)"/>
            <column name="first_name" type="varchar(50)"/>
            <column name="last_name" type="varchar(50)"/>
            <column name="email" type="varchar(100)"/>
        </createTable>

        <createTable tableName="T_AUTHORITY">
            <column name="name" type="varchar(255)">
                <constraints primaryKey="true" nullable="false"/>
            </column>
        </createTable>

        <createTable tableName="T_USER_AUTHORITY">
            <column name="login" type="varchar(50)">
                <constraints nullable="false"/>
            </column>
            <column name="name" type="varchar(255)">
                <constraints nullable="false"/>
            </column>
        </createTable>
        <addPrimaryKey columnNames="login, name" tableName="T_USER_AUTHORITY"/>

        <createTable tableName="T_PERSISTENT_TOKEN">
            <column name="series" type="varchar(255)">
                <constraints primaryKey="true" nullable="false"/>
            </column>
            <column name="user_login" type="varchar(50)"/>
            <column name="token_value" type="varchar(255)"/>
            <column name="token_date" type="date"/>
            <column name="ip_address" type="varchar(39)"/>
            <column name="user_agent" type="varchar(255)"/>
        </createTable>

        <createTable tableName="HIBERNATE_SEQUENCES">
            <column name="sequence_name" type="varchar(255)"/>
            <column name="sequence_next_hi_value" type="integer"/>
        </createTable>

        <createIndex indexName="idx_user_authority"
                     tableName="T_USER_AUTHORITY"
                     unique="true">
            <column name="login" type="varchar(50)"/>
            <column name="name" type="varchar(255)"/>
        </createIndex>

        <addForeignKeyConstraint baseColumnNames="name"
                                 baseTableName="T_USER_AUTHORITY"
                                 constraintName="fk_authority_name"
                                 referencedColumnNames="name"
                                 referencedTableName="T_AUTHORITY"/>

        <addForeignKeyConstraint baseColumnNames="login"
                                 baseTableName="T_USER_AUTHORITY"
                                 constraintName="fk_user_login"
                                 referencedColumnNames="login"
                                 referencedTableName="T_USER"/>

        <addForeignKeyConstraint baseColumnNames="user_login"
                                 baseTableName="T_PERSISTENT_TOKEN"
                                 constraintName="fk_user_persistent_token"
                                 referencedColumnNames="login"
                                 referencedTableName="T_USER"/>

        <loadData encoding="UTF-8"
                  file="config/liquibase/users.csv"
                  separator=";"
                  tableName="T_USER"/>

        <loadData encoding="UTF-8"
                  file="config/liquibase/authorities.csv"
                  separator=";"
                  tableName="T_AUTHORITY"/>

        <loadData encoding="UTF-8"
                  file="config/liquibase/users_authorities.csv"
                  separator=";"
                  tableName="T_USER_AUTHORITY"/>
    </changeSet>

    <!-- Manage the new Springboot actuator Audit event -->
    <changeSet id="2" author="jhipster">
        <createTable tableName="T_PERSISTENT_AUDIT_EVENT">
            <column name="event_id" type="bigint" >
                <constraints primaryKey="true" nullable="false"/>
            </column>
            <column name="principal" type="varchar(50)"/>
            <column name="event_date" type="date"/>
            <column name="event_type" type="varchar(50)"/>
        </createTable>

        <createTable tableName="T_PERSISTENT_AUDIT_EVENT_DATA">
            <column name="event_id" type="bigint">
                <constraints nullable="false"/>
            </column>
            <column name="name" type="varchar(50)">
                <constraints nullable="false"/>
            </column>
            <column name="value" type="varchar(255)"/>
        </createTable>
        <addPrimaryKey columnNames="event_id, name" tableName="T_PERSISTENT_AUDIT_EVENT_DATA"/>

        <createIndex indexName="idx_persistent_audit_event"
                     tableName="T_PERSISTENT_AUDIT_EVENT"
                     unique="false">
            <column name="principal" type="varchar(50)"/>
            <column name="event_date" type="timestamp"/>
        </createIndex>

        <createIndex indexName="idx_persistent_audit_event_data"
                     tableName="T_PERSISTENT_AUDIT_EVENT_DATA"
                     unique="false">
            <column name="event_id" type="bigint"/>
        </createIndex>

        <addForeignKeyConstraint baseColumnNames="event_id"
                                 baseTableName="T_PERSISTENT_AUDIT_EVENT_DATA"
                                 constraintName="FK_event_persistent_audit_event_data"
                                 referencedColumnNames="event_id"
                                 referencedTableName="T_PERSISTENT_AUDIT_EVENT"/>
    </changeSet>
</databaseChangeLog>
