<?xml version="1.0" encoding="UTF-8"?>

<configuration scan="true">
    <appender name="CONSOLE" class="ch.qos.logback.core.ConsoleAppender">
        <encoder>
            <charset>utf-8</charset>
            <Pattern>[%p] %c - %m%n</Pattern>
        </encoder>
    </appender>

    <appender name="FILE" class="ch.qos.logback.core.rolling.RollingFileAppender">
        <rollingPolicy class="ch.qos.logback.core.rolling.TimeBasedRollingPolicy">
            <fileNamePattern>logFile.%d{yyyy-MM-dd}.log</fileNamePattern>
            <maxHistory>90</maxHistory>
        </rollingPolicy>
        <encoder>
            <charset>utf-8</charset>
            <Pattern>%d %-5level [%thread] %logger{0}: %msg%n</Pattern>
        </encoder>
    </appender>

    <appender name="ASYNC" class="ch.qos.logback.classic.AsyncAppender">
        <queueSize>512</queueSize>
        <appender-ref ref="FILE"/>
    </appender>
	
    <logger name="<%=packageName%>" level="DEBUG"/>
    <logger name="org.apache.catalina.startup.DigesterFactory" level="OFF"/>
    <logger name="org.hibernate.ejb.HibernatePersistence" level="OFF"/>
    
    <contextListener class="ch.qos.logback.classic.jul.LevelChangePropagator">
        <resetJUL>true</resetJUL>
    </contextListener>

    <root level="WARN">
        <appender-ref ref="CONSOLE"/>
    </root>

</configuration>
